<?xml version="1.0" encoding="utf-8" ?>
<dwsync>
<file name="eksamensForside.png" server="ftp.thomasdsiemsen.com" local="131923972330631590" remote="131925640200000000" Dst="1" />
<file name="fisketur.png" server="ftp.thomasdsiemsen.com" local="131924713559031304" remote="131925640200000000" Dst="1" />
<file name="ganttKort.png" server="ftp.thomasdsiemsen.com" local="131924918103061631" remote="131925640200000000" Dst="1" />
<file name="logo.png" server="ftp.thomasdsiemsen.com" local="131917247997108465" remote="131925640200000000" Dst="1" />
<file name="sejltur.jpg" server="ftp.thomasdsiemsen.com" local="131831732224546085" remote="131925640200000000" Dst="1" />
<file name="logoArbejde.png" server="ftp.thomasdsiemsen.com" local="131925599208562075" remote="131925640200000000" Dst="1" />
<file name="sitemap.png" server="ftp.thomasdsiemsen.com" local="131917266228403437" remote="131925640200000000" Dst="1" />
<file name="sejltur.jpg.png" server="ftp.thomasdsiemsen.com" local="131923826055729178" remote="131925640200000000" Dst="1" />
<file name="sweetbotForside.png" server="ftp.thomasdsiemsen.com" local="131922384049375299" remote="131925640200000000" Dst="1" />
<file name="sweetbotIkoner.png" server="ftp.thomasdsiemsen.com" local="131921380858622704" remote="131925640200000000" Dst="1" />
<file name="sweetbotIkonRettelser.png" server="ftp.thomasdsiemsen.com" local="131921290720803501" remote="131925640200000000" Dst="1" />
<file name="sweetbotRemake.png" server="ftp.thomasdsiemsen.com" local="131921376158282804" remote="131925640200000000" Dst="1" />
<file name="vejrAppBrugermanual.png" server="ftp.thomasdsiemsen.com" local="131923950308294027" remote="131925640200000000" Dst="1" />
<file name="vejrAppForside.png" server="ftp.thomasdsiemsen.com" local="131922381343259479" remote="131925640200000000" Dst="1" />
<file name="vejrAppForskel.png" server="ftp.thomasdsiemsen.com" local="131918736981987032" remote="131925640200000000" Dst="1" />
<file name="sweetbotSkitser.png" server="ftp.thomasdsiemsen.com" local="131921413265257227" remote="131925640200000000" Dst="1" />
<file name="vejrAppIkonerRemake.png" server="ftp.thomasdsiemsen.com" local="131918696033945097" remote="131925640200000000" Dst="1" />
<file name="vejrAppPersonaer.png" server="ftp.thomasdsiemsen.com" local="131918687620213718" remote="131925640200000000" Dst="1" />
<file name="vejrAppSkitser.png" server="ftp.thomasdsiemsen.com" local="131918697878232647" remote="131925640200000000" Dst="1" />
<file name="vejrAppUdviklingsproces.png" server="ftp.thomasdsiemsen.com" local="131923947483328446" remote="131925640200000000" Dst="1" />
<file name="vejrAppTabletRemake.png" server="ftp.thomasdsiemsen.com" local="131918711035622714" remote="131925640200000000" Dst="1" />
<file name="xdPortfolioForside.png" server="ftp.thomasdsiemsen.com" local="131923915161180190" remote="131925640200000000" Dst="1" />
<file name="wireframe.png" server="ftp.thomasdsiemsen.com" local="131918641712757151" remote="131925640200000000" Dst="1" />
<file name="xdPortfolioGrid.png" server="ftp.thomasdsiemsen.com" local="131923034623550825" remote="131925640200000000" Dst="1" />
<file name="xdPortfolioOversigt.png" server="ftp.thomasdsiemsen.com" local="131925621330904584" remote="131925640200000000" Dst="1" />
<file name="forsideBillede.png" server="ftp.thomasdsiemsen.com" local="131924852009423202" remote="131925640200000000" Dst="1" />
</dwsync>